{
  "main": {
    "id": "64a6f01a67c7a05e",
    "type": "split",
    "children": [
      {
        "id": "706625a8b60d2a38",
        "type": "tabs",
        "children": [
          {
            "id": "8114516ae320fcfd",
            "type": "leaf",
            "state": {
              "type": "pdf",
              "state": {
                "file": "外部资料/Linux内核/x86汇编语言：从实模式到保护模式（第2版）离线图片加完整书签，并且去重，重新制作 (李忠 王晓波 余洁) (Z-Library).pdf"
              },
              "icon": "lucide-file-text",
              "title": "x86汇编语言：从实模式到保护模式（第2版）离线图片加完整书签，并且去重，重新制作 (李忠 王晓波 余洁) (Z-Library)"
            }
          },
          {
            "id": "a067a92ffda076ef",
            "type": "leaf",
            "state": {
              "type": "markdown",
              "state": {
                "file": "Linux内核开发/内核开发/01-BIOS相关资料.md",
                "mode": "source",
                "source": false
              },
              "icon": "lucide-file",
              "title": "01-BIOS相关资料"
            }
          }
        ],
        "currentTab": 1
      }
    ],
    "direction": "vertical"
  },
  "left": {
    "id": "e69962d2d53fc2c8",
    "type": "split",
    "children": [
      {
        "id": "6268c784ade9e775",
        "type": "tabs",
        "children": [
          {
            "id": "793bf92be4ad1e8f",
            "type": "leaf",
            "state": {
              "type": "file-explorer",
              "state": {
                "sortOrder": "alphabetical",
                "autoReveal": false
              },
              "icon": "lucide-folder-closed",
              "title": "文件列表"
            }
          },
          {
            "id": "216907a4a2fbb92f",
            "type": "leaf",
            "state": {
              "type": "search",
              "state": {
                "query": "",
                "matchingCase": false,
                "explainSearch": false,
                "collapseAll": false,
                "extraContext": false,
                "sortOrder": "alphabetical"
              },
              "icon": "lucide-search",
              "title": "搜索"
            }
          },
          {
            "id": "6b60bf01d7ea37ee",
            "type": "leaf",
            "state": {
              "type": "bookmarks",
              "state": {},
              "icon": "lucide-bookmark",
              "title": "书签"
            }
          }
        ]
      }
    ],
    "direction": "horizontal",
    "width": 340.5,
    "collapsed": true
  },
  "right": {
    "id": "dce949218fa26760",
    "type": "split",
    "children": [
      {
        "id": "30b18b9a72ac476c",
        "type": "tabs",
        "children": [
          {
            "id": "d9e26722736cfff1",
            "type": "leaf",
            "state": {
              "type": "backlink",
              "state": {
                "file": "Linux内核开发/gpio驱动/1602A.md",
                "collapseAll": false,
                "extraContext": false,
                "sortOrder": "alphabetical",
                "showSearch": false,
                "searchQuery": "",
                "backlinkCollapsed": false,
                "unlinkedCollapsed": true
              },
              "icon": "links-coming-in",
              "title": "1602A 的反向链接列表"
            }
          },
          {
            "id": "598125fc4b328988",
            "type": "leaf",
            "state": {
              "type": "outgoing-link",
              "state": {
                "file": "欢迎.md",
                "linksCollapsed": false,
                "unlinkedCollapsed": true
              },
              "icon": "links-going-out",
              "title": "欢迎 的出链列表"
            }
          },
          {
            "id": "2721da4a68d16018",
            "type": "leaf",
            "state": {
              "type": "tag",
              "state": {
                "sortOrder": "frequency",
                "useHierarchy": true,
                "showSearch": false,
                "searchQuery": ""
              },
              "icon": "lucide-tags",
              "title": "标签"
            }
          },
          {
            "id": "e21a57e54ee93394",
            "type": "leaf",
            "state": {
              "type": "outline",
              "state": {
                "file": "Linux内核开发/gpio驱动/1602A.md",
                "followCursor": false,
                "showSearch": false,
                "searchQuery": ""
              },
              "icon": "lucide-list",
              "title": "1602A 的大纲"
            }
          },
          {
            "id": "ef54d39a521d6425",
            "type": "leaf",
            "state": {
              "type": "copilot-chat-view",
              "state": {},
              "icon": "message-square",
              "title": "Copilot"
            }
          },
          {
            "id": "6f28ba905e9b4bfd",
            "type": "leaf",
            "state": {
              "type": "smtcmp-chat-view",
              "state": {},
              "icon": "lucide-file",
              "title": "Plugin no longer active"
            }
          },
          {
            "id": "67f9d80b93aa5986",
            "type": "leaf",
            "state": {
              "type": "git-view",
              "state": {},
              "icon": "git-pull-request",
              "title": "Source Control"
            }
          }
        ],
        "currentTab": 4
      }
    ],
    "direction": "horizontal",
    "width": 421.5,
    "collapsed": true
  },
  "left-ribbon": {
    "hiddenItems": {
      "switcher:打开快速切换": false,
      "graph:查看关系图谱": false,
      "canvas:新建白板": false,
      "daily-notes:打开/创建今天的日记": false,
      "templates:插入模板": false,
      "command-palette:打开命令面板": false,
      "markdown-importer:打开 Markdown 格式转换器": false,
      "obsidian-excalidraw-plugin:新建绘图文件": false,
      "copilot:Open Copilot Chat": false,
      "smart-composer:Open smart composer": false,
      "obsidian-textgenerator-plugin:Generate Text!": false,
      "obsidian-textgenerator-plugin:Text Generator: Templates Packages Manager": false,
      "templater-obsidian:Templater": false,
      "obsidian-git:Open Git source control": false
    }
  },
  "active": "a067a92ffda076ef",
  "lastOpenFiles": [
    "外部资料/Linux内核/x86汇编语言：从实模式到保护模式（第2版）离线图片加完整书签，并且去重，重新制作 (李忠 王晓波 余洁) (Z-Library).pdf",
    "Linux内核开发/内核开发/01-BIOS相关资料.md",
    "Linux内核开发/内核开发/04-终端显示颜色.md",
    "Linux内核开发/内核开发/03-GDT全局表述符.md",
    "Linux内核开发/内核开发/00-NASM汇编语言中的高级操作.md",
    "Linux内核开发/内核开发/ShiMoShiNeiCunFenBu.png",
    "Linux内核开发/内核开发/DuanXuanZeZi.png",
    "Linux内核开发/内核开发/DuanMiaoShuFuYuNeiCunDuanDeGuanXi.png",
    "Linux内核开发/内核开发/DuanMiaoShuFuGeShi.png",
    "Linux内核开发/内核开发/02-ASCII码表.md",
    "Linux内核开发/内核开发",
    "Linux内核开发/未命名文件夹",
    "外部资料/Linux内核/80x86保护模式系列教程 (it-ebooks) (Z-Library).epub",
    "外部资料/Linux内核/Intel 80386 程序员参考手册 (it-ebooks) (Z-Library).epub",
    "外部资料/Linux内核/C和指针 (里科) (Z-Library).pdf",
    "PPT测试.md",
    "Linux内核开发/gpio驱动/1602A.md",
    "外部资料/1602A资料.md",
    "background.jpeg",
    "copilot-conversations/[[1602A]]整理一下这个文档@20250221_025604.md",
    "copilot-conversations",
    "冒泡排序.md",
    "textgenerator/templates/awesomePrompts/developerrelationsconsultantAwesome.md",
    "textgenerator/templates/default/summarize.md",
    "textgenerator/templates/smartConnections/summarize.md",
    "Excalidraw/Drawing 2025-02-20 23.05.13.excalidraw.md",
    "textgenerator/templates/awesomePrompts/aitryingtoescapetheboxAwesome.md",
    "textgenerator/templates/default/simplify.md",
    "外部资料/嵌入式Linux设备驱动程序开发指南(原书第2版)2021【文字版】 (机械工业出版社) (Z-Library).pdf",
    "个人主页.md",
    "模版/实验记录模版.md",
    "模版",
    "芙蕖.jpeg",
    "textgenerator/templates/dalle/artStock.md",
    "textgenerator/templates/huggingface/summarizeBART.md",
    "textgenerator/templates/awesomePrompts/doctorAwesome.md",
    "textgenerator/templates/awesomePrompts/gnomistAwesome.md",
    "textgenerator/templates/awesomePrompts/classicalmusiccomposerAwesome.md",
    "textgenerator/templates/dalle/getPhoto.md",
    "textgenerator/templates/dalle/artDigital.md",
    "外部资料/1602A资料.pdf",
    "未命名.canvas"
  ]
}